reqs_diff/__init__.py
reqs_diff/compare.py
reqs_diff/__pycache__/__init__.cpython-310.pyc
reqs_diff/__pycache__/compare.cpython-310.pyc
reqs_diff-0.1.0.dist-info/LICENSE
reqs_diff-0.1.0.dist-info/METADATA
reqs_diff-0.1.0.dist-info/WHEEL
reqs_diff-0.1.0.dist-info/entry_points.txt
reqs_diff-0.1.0.dist-info/top_level.txt
reqs_diff-0.1.0.dist-info/RECORD
