Metadata-Version: 2.1
Name: reqs-diff
Version: 0.1.0
Summary: A tool to compare multiple requirements.txt files
Home-page: https://github.com/bricefotzo/reqs-diff
Author: Brice Fotzo
Author-email: bricef.tech@gmail.com
Classifier: Programming Language :: Python :: 3
Classifier: License :: OSI Approved :: MIT License
Classifier: Operating System :: OS Independent
Requires-Python: >=3.6
License-File: LICENSE
Requires-Dist: pandas
Requires-Dist: tabulate
Requires-Dist: termcolor
